django_mailbox/__init__.py
django_mailbox/admin.py
django_mailbox/apps.py
django_mailbox/google_utils.py
django_mailbox/models.py
django_mailbox/signals.py
django_mailbox/utils.py
django_mailbox/locale/ru_RU/LC_MESSAGES/django.mo
django_mailbox/locale/ru_RU/LC_MESSAGES/django.po
django_mailbox/management/__init__.py
django_mailbox/management/commands/__init__.py
django_mailbox/management/commands/getmail.py
django_mailbox/management/commands/processincomingmessage.py
django_mailbox/management/commands/rebuildmessageattachments.py
django_mailbox/migrations/0001_initial.py
django_mailbox/migrations/0002_add_eml_to_message.py
django_mailbox/migrations/0003_auto_20150409_0316.py
django_mailbox/migrations/0004_bytestring_to_unicode.py
django_mailbox/migrations/0005_auto_20160523_2240.py
django_mailbox/migrations/0006_mailbox_last_polling.py
django_mailbox/migrations/0007_auto_20180421_0026.py
django_mailbox/migrations/0008_auto_20190219_1553.py
django_mailbox/migrations/__init__.py
django_mailbox/south_migrations/0001_initial.py
django_mailbox/south_migrations/0002_auto__chg_field_mailbox_uri.py
django_mailbox/south_migrations/0003_auto__add_field_mailbox_active.py
django_mailbox/south_migrations/0004_auto__add_field_message_outgoing.py
django_mailbox/south_migrations/0005_rename_fields.py
django_mailbox/south_migrations/0006_auto__add_field_message_in_reply_to.py
django_mailbox/south_migrations/0007_auto__del_field_message_address__add_field_message_from_header__add_fi.py
django_mailbox/south_migrations/0008_populate_from_to_fields.py
django_mailbox/south_migrations/0009_remove_references_table.py
django_mailbox/south_migrations/0010_auto__add_field_mailbox_from_email.py
django_mailbox/south_migrations/0011_auto__add_field_message_read.py
django_mailbox/south_migrations/0012_auto__add_messageattachment.py
django_mailbox/south_migrations/0013_auto__add_field_messageattachment_message.py
django_mailbox/south_migrations/0014_migrate_message_attachments.py
django_mailbox-4.8.2.dist-info/LICENSE
django_mailbox-4.8.2.dist-info/METADATA
django_mailbox-4.8.2.dist-info/WHEEL
django_mailbox-4.8.2.dist-info/top_level.txt
django_mailbox-4.8.2.dist-info/RECORD
